{
  "testEnvironment": "node",
  "testEnvironmentOptions": {
    "globalsCleanup": "on"
  },
  "transform": {
    "^.+\\.(js|jsx|ts|tsx|mjs)$": "babel-jest"
  },
  "moduleFileExtensions": ["ts", "js", "mjs", "json", "node"],
  "testMatch": ["**/src/**/*.test.ts"],
  "coverageDirectory": "coverage",
  "coverageReporters": ["json", "text"],
  "collectCoverageFrom": ["**/src/**/*"],
  "transformIgnorePatterns": [],
  "extensionsToTreatAsEsm": [".ts"],
  "globals": {
    "ts-jest": {
      "useESM": true
    }
  }
}
